{
  "slices": {
    "components": {
      "my_slice": {
        "library": "slices",
        "id": "my_slice",
        "name": "MySlice",
        "description": "MySlice",
        "model": {
          "id": "my_slice",
          "type": "SharedSlice",
          "name": "MySlice",
          "description": "MySlice",
          "variations": [
            {
              "id": "default-slice",
              "name": "Default slice",
              "docURL": "...",
              "version": "sktwi1xtmkfgx8626",
              "description": "MySlice",
              "primary": {},
              "items": {
                "image": {
                  "config": {
                    "label": "image",
                    "constraint": {},
                    "thumbnails": []
                  },
                  "type": "Image"
                },
                "title": {
                  "config": {
                    "label": "title",
                    "placeholder": ""
                  },
                  "type": "Text"
                },
                "description": {
                  "config": {
                    "label": "description",
                    "placeholder": "",
                    "allowTargetBlank": true,
                    "single": "paragraph,preformatted,heading1,heading2,heading3,heading4,heading5,heading6,strong,em,hyperlink,image,embed,list-item,o-list-item,rtl"
                  },
                  "type": "StructuredText"
                }
              }
            }
          ]
        },
        "mocks": {
          "default-slice": {
            "variation": "default-slice",
            "name": "Default slice",
            "slice_type": "my_slice",
            "items": [
              {
                "image": {
                  "dimensions": {
                    "width": 900,
                    "height": 500
                  },
                  "alt": "Placeholder image",
                  "copyright": null,
                  "url": "https://images.unsplash.com/photo-1593642532973-d31b6557fa68?w=900&h=500&fit=crop"
                },
                "title": "matrix transparent e-services",
                "description": [
                  {
                    "type": "paragraph",
                    "text": "In enim aliquip cupidatat nostrud ex sint aute.",
                    "spans": []
                  }
                ]
              },
              {
                "image": {
                  "dimensions": {
                    "width": 900,
                    "height": 500
                  },
                  "alt": "Placeholder image",
                  "copyright": null,
                  "url": "https://images.unsplash.com/photo-1571126770897-2d612d1f7b89?w=900&h=500&fit=crop"
                },
                "title": "optimize out-of-the-box niches",
                "description": [
                  {
                    "type": "paragraph",
                    "text": "Eu nostrud nisi ad ea non cupidatat deserunt fugiat consequat. Duis eiusmod pariatur sint sint in.",
                    "spans": []
                  }
                ]
              },
              {
                "image": {
                  "dimensions": {
                    "width": 900,
                    "height": 500
                  },
                  "alt": "Placeholder image",
                  "copyright": null,
                  "url": "https://images.unsplash.com/photo-1589652717521-10c0d092dea9?w=900&h=500&fit=crop"
                },
                "title": "revolutionize dot-com models",
                "description": [
                  {
                    "type": "paragraph",
                    "text": "Tempor dolor esse ea proident reprehenderit officia anim. Commodo Lorem enim sint ad reprehenderit.",
                    "spans": []
                  }
                ]
              }
            ],
            "primary": {}
          }
        },
        "meta": {
          "fileName": "index",
          "isDirectory": true,
          "extension": "js"
        },
        "screenshotPaths": {
          "default-slice": {
            "path": "/Users/kumardeepanshu/Desktop/code/cyphen-innovations/my-blog/.slicemachine/assets/slices/MySlice/default-slice/preview.png",
            "width": 800,
            "height": 30
          }
        }
      },
      "posts_cards": {
        "library": "slices",
        "id": "posts_cards",
        "name": "PostsCards",
        "description": "PostsCards",
        "model": {
          "id": "posts_cards",
          "type": "SharedSlice",
          "name": "PostsCards",
          "description": "PostsCards",
          "variations": [
            {
              "id": "default-slice",
              "name": "Default slice",
              "docURL": "...",
              "version": "sktwi1xtmkfgx8626",
              "description": "PostsCards",
              "primary": {},
              "items": {
                "image": {
                  "config": {
                    "label": "image",
                    "constraint": {},
                    "thumbnails": []
                  },
                  "type": "Image"
                },
                "title": {
                  "config": {
                    "label": "title",
                    "placeholder": ""
                  },
                  "type": "Text"
                },
                "description": {
                  "config": {
                    "label": "description",
                    "placeholder": "",
                    "allowTargetBlank": true,
                    "single": "paragraph,preformatted,heading1,heading2,heading3,heading4,heading5,heading6,strong,em,hyperlink,image,embed,list-item,o-list-item,rtl"
                  },
                  "type": "StructuredText"
                },
                "blogLink": {
                  "config": {
                    "label": "blogLink",
                    "placeholder": "",
                    "allowTargetBlank": false
                  },
                  "type": "Link"
                }
              }
            }
          ]
        },
        "mocks": {
          "default-slice": {
            "variation": "default-slice",
            "name": "Default slice",
            "slice_type": "posts_cards",
            "items": [
              {
                "image": {
                  "dimensions": {
                    "width": 900,
                    "height": 500
                  },
                  "alt": "Placeholder image",
                  "copyright": null,
                  "url": "https://images.unsplash.com/photo-1493119508027-2b584f234d6c?w=900&h=500&fit=crop"
                },
                "title": "envisioneer bricks-and-clicks applications",
                "description": [
                  {
                    "type": "paragraph",
                    "text": "Nulla occaecat officia consequat proident ipsum ut esse ad consectetur esse excepteur reprehenderit id amet. Ut reprehenderit amet aliquip excepteur sint deserunt nisi est irure esse eiusmod dolore ad quis.",
                    "spans": []
                  }
                ],
                "blogLink": {
                  "link_type": "Web",
                  "url": "https://slicemachine.dev"
                }
              },
              {
                "image": {
                  "dimensions": {
                    "width": 900,
                    "height": 500
                  },
                  "alt": "Placeholder image",
                  "copyright": null,
                  "url": "https://images.unsplash.com/photo-1587614295999-6c1c13675117?w=900&h=500&fit=crop"
                },
                "title": "iterate user-centric paradigms",
                "description": [
                  {
                    "type": "paragraph",
                    "text": "Non ex esse irure cupidatat do occaecat magna enim elit est. Amet non sit labore cillum elit laborum cillum ea dolore veniam pariatur deserunt aliquip elit exercitation. Esse aliquip anim aliquip duis voluptate aliquip commodo.",
                    "spans": []
                  }
                ],
                "blogLink": {
                  "link_type": "Web",
                  "url": "http://twitter.com"
                }
              },
              {
                "image": {
                  "dimensions": {
                    "width": 900,
                    "height": 500
                  },
                  "alt": "Placeholder image",
                  "copyright": null,
                  "url": "https://images.unsplash.com/photo-1496181133206-80ce9b88a853?w=900&h=500&fit=crop"
                },
                "title": "grow enterprise action-items",
                "description": [
                  {
                    "type": "paragraph",
                    "text": "Enim sit cillum mollit culpa aute nostrud do nulla commodo eu est dolore commodo deserunt duis. Mollit aute dolore laboris proident officia excepteur velit laborum commodo reprehenderit dolor aliqua nulla aliqua. Minim aliqua sunt duis minim occaecat elit ex culpa amet excepteur deserunt amet.",
                    "spans": []
                  }
                ],
                "blogLink": {
                  "link_type": "Web",
                  "url": "http://google.com"
                }
              },
              {
                "image": {
                  "dimensions": {
                    "width": 900,
                    "height": 500
                  },
                  "alt": "Placeholder image",
                  "copyright": null,
                  "url": "https://images.unsplash.com/photo-1587613865763-4b8b0d19e8ab?w=900&h=500&fit=crop"
                },
                "title": "scale out-of-the-box e-tailers",
                "description": [
                  {
                    "type": "paragraph",
                    "text": "Eu aliqua aliqua qui esse aute aliqua excepteur deserunt ullamco duis est.",
                    "spans": []
                  }
                ],
                "blogLink": {
                  "link_type": "Web",
                  "url": "http://twitter.com"
                }
              }
            ],
            "primary": {}
          }
        },
        "meta": {
          "fileName": "index",
          "isDirectory": true,
          "extension": "js"
        },
        "screenshotPaths": {
          "default-slice": {
            "path": "/Users/kumardeepanshu/Desktop/code/cyphen-innovations/my-blog/.slicemachine/assets/slices/PostsCards/default-slice/preview.png",
            "width": 800,
            "height": 605
          }
        }
      }
    }
  }
}